aws_custom_ews_kafka_topic/__init__.py
aws_custom_ews_kafka_topic/custom.py
aws_custom_ews_kafka_topic/resource.py
aws_custom_ews_kafka_topic-0.0.3.dist-info/AUTHORS.rst
aws_custom_ews_kafka_topic-0.0.3.dist-info/LICENSE
aws_custom_ews_kafka_topic-0.0.3.dist-info/METADATA
aws_custom_ews_kafka_topic-0.0.3.dist-info/NOTICES.rst
aws_custom_ews_kafka_topic-0.0.3.dist-info/WHEEL
aws_custom_ews_kafka_topic-0.0.3.dist-info/top_level.txt
aws_custom_ews_kafka_topic-0.0.3.dist-info/RECORD
