Metadata-Version: 2.1
Name: aws-custom-ews-kafka-topic
Version: 0.0.3
Summary: Lib to represent kafka topic in Troposphere
Home-page: https://github.com/johnpreston/aws_custom_ews_kafka_topic
Author: John Mille
Author-email: john@ews-network.net
License: MPL-2.0
Keywords: aws_custom_ews_kafka_topic
Platform: UNKNOWN
Classifier: Development Status :: 2 - Pre-Alpha
Classifier: Intended Audience :: Developers
Classifier: Intended Audience :: System Administrators
Classifier: Intended Audience :: Information Technology
Classifier: License :: OSI Approved :: Mozilla Public License 2.0 (MPL 2.0)
Classifier: Programming Language :: Python :: 3
Classifier: Programming Language :: Python :: 3.6
Classifier: Programming Language :: Python :: 3.7
Classifier: Programming Language :: Python :: 3.8
Requires-Python: >=3.6
Requires-Dist: troposphere (==2.7.0)
